browserdebuggertools/__init__.py
browserdebuggertools/eventhandlers.py
browserdebuggertools/exceptions.py
browserdebuggertools/models.py
browserdebuggertools/utils.py
browserdebuggertools/wssessionmanager.py
browserdebuggertools/chrome/__init__.py
browserdebuggertools/chrome/interface.py
tests/__init__.py
tests/e2etests/__init__.py
tests/e2etests/chrome/__init__.py
tests/e2etests/chrome/test_interface.py
tests/e2etests/testsite/__init__.py
tests/e2etests/testsite/start.py
tests/integrationtests/__init__.py
tests/integrationtests/test_wssessionmanager.py
tests/integrationtests/chrome/__init__.py
tests/integrationtests/chrome/test_interface.py
tests/unittests/__init__.py
tests/unittests/test_eventhandlers.py
tests/unittests/test_models.py
tests/unittests/test_wssessionmanager.py
tests/unittests/chrome/__init__.py
tests/unittests/chrome/test_interface.py
browserdebuggertools-6.0.3.dist-info/LICENSE.txt
browserdebuggertools-6.0.3.dist-info/METADATA
browserdebuggertools-6.0.3.dist-info/WHEEL
browserdebuggertools-6.0.3.dist-info/top_level.txt
browserdebuggertools-6.0.3.dist-info/RECORD
