Metadata-Version: 2.1
Name: browserdebuggertools
Version: 6.0.3
Summary: A client which calls remote web browser debugger methods
Home-page: https://github.com/scivisum/browser-debugger-tools
Author: ThinkTribe LTD
Author-email: rd@scivisum.co.uk
License: GNU General Public License v3
Platform: UNKNOWN
Classifier: Intended Audience :: Developers
Classifier: Programming Language :: Python
Classifier: Programming Language :: Python :: 3
Classifier: License :: OSI Approved :: GNU General Public License v3 (GPLv3)
Classifier: Operating System :: OS Independent
Requires-Python: >=3.8
License-File: LICENSE.txt
Requires-Dist: requests
Requires-Dist: typing
Requires-Dist: websocket-client
